mcpower-0.3.3.dist-info/RECORD
mcpower-0.3.3.dist-info/WHEEL
mcpower-0.3.3.dist-info/top_level.txt
mcpower-0.3.3.dist-info/METADATA
mcpower-0.3.3.dist-info/licenses/LICENSE
mcpower/__init__.py
mcpower/linear_regression.py
mcpower/base.py
mcpower/utils/formatters.py
mcpower/utils/ols_compiled.cpython-311-darwin.so
mcpower/utils/updates.py
mcpower/utils/validators.py
mcpower/utils/ols.py
mcpower/utils/data_generation.py
mcpower/utils/__init__.py
mcpower/utils/parsers.py
mcpower/utils/data_generation_compiled.cpython-312-darwin.so
mcpower/utils/visualization.py
mcpower/utils/ols_compiled.cpython-310-darwin.so
mcpower/utils/data_generation_compiled.cpython-311-darwin.so
mcpower/utils/ols_compiled.cpython-312-darwin.so
mcpower/utils/data_generation_compiled.cpython-310-darwin.so
