Metadata-Version: 2.4
Name: MCPower
Version: 0.3.3
Summary: Monte Carlo Power Analysis for Statistical Models
Home-page: https://github.com/pawlenartowicz/MCPower
Author: Paweł Lenartowicz
Author-email: pawellenartowicz@europe.com
Keywords: power analysis,statistics,monte carlo,linear regression
Classifier: Development Status :: 4 - Beta
Classifier: Intended Audience :: Science/Research
Classifier: License :: OSI Approved :: GNU General Public License v3 or later (GPLv3+)
Classifier: Programming Language :: Python :: 3
Classifier: Programming Language :: Python :: 3.10
Classifier: Programming Language :: Python :: 3.11
Classifier: Programming Language :: Python :: 3.12
Classifier: Programming Language :: Python :: 3.13
Requires-Python: >=3.10
License-File: LICENSE
Requires-Dist: numpy>=2.0.0
Requires-Dist: pandas>=2.0.0
Requires-Dist: matplotlib>=3.8.0
Requires-Dist: scipy>=1.11.0
Provides-Extra: jit
Requires-Dist: numba>=0.61.0; extra == "jit"
Provides-Extra: parallel
Requires-Dist: joblib>=1.3.0; extra == "parallel"
Provides-Extra: dev
Requires-Dist: pytest>=7.0.0; extra == "dev"
Requires-Dist: pytest-cov>=4.0.0; extra == "dev"
Requires-Dist: build>=0.10.0; extra == "dev"
Requires-Dist: twine>=4.0.0; extra == "dev"
Provides-Extra: all
Requires-Dist: joblib>=1.3.0; extra == "all"
Requires-Dist: pytest>=7.0.0; extra == "all"
Requires-Dist: pytest-cov>=4.0.0; extra == "all"
Dynamic: author
Dynamic: author-email
Dynamic: classifier
Dynamic: description
Dynamic: description-content-type
Dynamic: home-page
Dynamic: keywords
Dynamic: license-file
Dynamic: provides-extra
Dynamic: requires-dist
Dynamic: requires-python
Dynamic: summary
